myfy/__init__.py
myfy/frontend/__init__.py
myfy/frontend/assets.py
myfy/frontend/build.py
myfy/frontend/config.py
myfy/frontend/module.py
myfy/frontend/process.py
myfy/frontend/process.py.bak2
myfy/frontend/scaffold.py
myfy/frontend/static_files.py
myfy/frontend/templates.py
myfy/frontend/version.py
myfy/frontend/stubs/.gitignore
myfy/frontend/stubs/app.py
myfy/frontend/stubs/package.json
myfy/frontend/stubs/vite.config.js
myfy/frontend/stubs/frontend/css/input.css
myfy/frontend/stubs/frontend/js/main.js
myfy/frontend/stubs/frontend/js/theme-switcher.js
myfy/frontend/stubs/frontend/templates/base.html
myfy/frontend/stubs/frontend/templates/home.html
myfy/frontend/stubs/frontend/templates/components/button.html
myfy/frontend/stubs/frontend/templates/components/card.html
myfy/frontend/stubs/frontend/templates/components/form.html
myfy/frontend/stubs/frontend/templates/components/navbar.html
myfy_frontend-0.1.2.dist-info/METADATA
myfy_frontend-0.1.2.dist-info/WHEEL
myfy_frontend-0.1.2.dist-info/RECORD
