Metadata-Version: 2.4
Name: myfy-frontend
Version: 0.1.2
Summary: Frontend module for myfy with Tailwind 4, DaisyUI 5, and Vite
License: MIT
Requires-Python: >=3.12
Requires-Dist: jinja2>=3.1.0
Requires-Dist: myfy-core~=0.1.2
Requires-Dist: myfy-web~=0.1.2
Requires-Dist: pydantic>=2.0.0
Requires-Dist: starlette>=0.27.0
Provides-Extra: dev
Requires-Dist: pytest-asyncio>=0.23.0; extra == 'dev'
Requires-Dist: pytest>=8.0.0; extra == 'dev'
